[[{"tr3.hiddenLayers": 4, "tr1.epochs": 574, "tr1.hiddenLayers": 4, "tr2.epochs": 196, "tr2.testError": 0.4948627220227152, "tr2.hiddenLayers": 4, "tr3.testError": 0.5427541326513724, "tr3.epochs": 169, "tr1.testError": 0.46986910200076354}], [{"tr3.hiddenLayers": 8, "tr1.epochs": 592, "tr1.hiddenLayers": 8, "tr2.epochs": 187, "tr2.testError": 0.48429856912144953, "tr2.hiddenLayers": 8, "tr3.testError": 0.4852693653781137, "tr3.epochs": 155, "tr1.testError": 0.5081979216554673}], [{"tr3.hiddenLayers": 12, "tr1.epochs": 839, "tr1.hiddenLayers": 12, "tr2.epochs": 1491, "tr2.testError": 0.37464004672855306, "tr2.hiddenLayers": 12, "tr3.testError": 0.5622842188169568, "tr3.epochs": 622, "tr1.testError": 0.5053203881364619}], [{"tr3.hiddenLayers": 9, "tr1.epochs": 582, "tr1.hiddenLayers": 9, "tr2.epochs": 404, "tr2.testError": 0.4469375523428438, "tr2.hiddenLayers": 9, "tr3.testError": 0.47832382433540566, "tr3.epochs": 639, "tr1.testError": 0.48843148515036483}], [{"tr3.hiddenLayers": 7, "tr1.epochs": 552, "tr1.hiddenLayers": 7, "tr2.epochs": 325, "tr2.testError": 0.44227284077320855, "tr2.hiddenLayers": 7, "tr3.testError": 0.518982625116758, "tr3.epochs": 301, "tr1.testError": 0.47123696737622184}], [{"tr3.hiddenLayers": 9, "tr1.epochs": 611, "tr1.hiddenLayers": 9, "tr2.epochs": 705, "tr2.testError": 0.4305569938746572, "tr2.hiddenLayers": 9, "tr3.testError": 0.5984708555530701, "tr3.epochs": 810, "tr1.testError": 0.5027781002168148}], [{"tr3.hiddenLayers": 6, "tr1.epochs": 561, "tr1.hiddenLayers": 6, "tr2.epochs": 434, "tr2.testError": 0.4319698952846015, "tr2.hiddenLayers": 6, "tr3.testError": 0.436314015109697, "tr3.epochs": 748, "tr1.testError": 0.4455060541701863}], [{"tr3.hiddenLayers": 11, "tr1.epochs": 672, "tr1.hiddenLayers": 11, "tr2.epochs": 409, "tr2.testError": 0.46066188855407936, "tr2.hiddenLayers": 11, "tr3.testError": 0.5192404655097564, "tr3.epochs": 219, "tr1.testError": 0.476159726846466}], [{"tr3.hiddenLayers": 7, "tr1.epochs": 586, "tr1.hiddenLayers": 7, "tr2.epochs": 294, "tr2.testError": 0.4454517594603028, "tr2.hiddenLayers": 7, "tr3.testError": 0.40233610355485955, "tr3.epochs": 187, "tr1.testError": 0.4744652359628101}], [{"tr3.hiddenLayers": 9, "tr1.epochs": 804, "tr1.hiddenLayers": 9, "tr2.epochs": 279, "tr2.testError": 0.4774194100543902, "tr2.hiddenLayers": 9, "tr3.testError": 0.46872152157903396, "tr3.epochs": 439, "tr1.testError": 0.4348444905540135}], [{"tr3.hiddenLayers": 8, "tr1.epochs": 594, "tr1.hiddenLayers": 8, "tr2.epochs": 267, "tr2.testError": 0.4827882911480586, "tr2.hiddenLayers": 8, "tr3.testError": 0.3627439866447379, "tr3.epochs": 499, "tr1.testError": 0.5143851167534802}], [{"tr3.hiddenLayers": 8, "tr1.epochs": 626, "tr1.hiddenLayers": 8, "tr2.epochs": 1054, "tr2.testError": 0.4304737585692843, "tr2.hiddenLayers": 8, "tr3.testError": 0.4484299913934573, "tr3.epochs": 1025, "tr1.testError": 0.4917168511766706}], [{"tr3.hiddenLayers": 3, "tr1.epochs": 367, "tr1.hiddenLayers": 3, "tr2.epochs": 188, "tr2.testError": 0.4375603665050763, "tr2.hiddenLayers": 3, "tr3.testError": 0.42943338320196606, "tr3.epochs": 137, "tr1.testError": 0.4264951185430203}], [{"tr3.hiddenLayers": 6, "tr1.epochs": 606, "tr1.hiddenLayers": 6, "tr2.epochs": 474, "tr2.testError": 0.466996153510268, "tr2.hiddenLayers": 6, "tr3.testError": 0.5066730837875869, "tr3.epochs": 751, "tr1.testError": 0.45349384688688327}], [{"tr3.hiddenLayers": 9, "tr1.epochs": 797, "tr1.hiddenLayers": 9, "tr2.epochs": 380, "tr2.testError": 0.5035154216705336, "tr2.hiddenLayers": 9, "tr3.testError": 0.5691930813372583, "tr3.epochs": 454, "tr1.testError": 0.4543247023372668}], [{"tr3.hiddenLayers": 15, "tr1.epochs": 878, "tr1.hiddenLayers": 15, "tr2.epochs": 544, "tr2.testError": 0.4464102645986522, "tr2.hiddenLayers": 15, "tr3.testError": 0.4829957647898859, "tr3.epochs": 488, "tr1.testError": 0.5335725248255099}], [{"tr3.hiddenLayers": 9, "tr1.epochs": 1008, "tr1.hiddenLayers": 9, "tr2.epochs": 208, "tr2.testError": 0.5690460197381786, "tr2.hiddenLayers": 9, "tr3.testError": 0.7360808613573913, "tr3.epochs": 268, "tr1.testError": 0.4594935134733261}], [{"tr3.hiddenLayers": 5, "tr1.epochs": 366, "tr1.hiddenLayers": 5, "tr2.epochs": 289, "tr2.testError": 0.49211709783775703, "tr2.hiddenLayers": 5, "tr3.testError": 0.6326289502287561, "tr3.epochs": 450, "tr1.testError": 0.4502192953674902}], [{"tr3.hiddenLayers": 6, "tr1.epochs": 430, "tr1.hiddenLayers": 6, "tr2.epochs": 283, "tr2.testError": 0.4448553129904804, "tr2.hiddenLayers": 6, "tr3.testError": 0.40140521742704033, "tr3.epochs": 218, "tr1.testError": 0.4374133791953161}], [{"tr3.hiddenLayers": 11, "tr1.epochs": 713, "tr1.hiddenLayers": 11, "tr2.epochs": 457, "tr2.testError": 0.42931741803284, "tr2.hiddenLayers": 11, "tr3.testError": 0.372535720340383, "tr3.epochs": 278, "tr1.testError": 0.4935782522779405}], [{"tr3.hiddenLayers": 13, "tr1.epochs": 969, "tr1.hiddenLayers": 13, "tr2.epochs": 605, "tr2.testError": 0.48290527256183163, "tr2.hiddenLayers": 13, "tr3.testError": 0.5312485310761016, "tr3.epochs": 382, "tr1.testError": 0.5371859704593945}], [{"tr3.hiddenLayers": 12, "tr1.epochs": 736, "tr1.hiddenLayers": 12, "tr2.epochs": 220, "tr2.testError": 0.4264554352577582, "tr2.hiddenLayers": 12, "tr3.testError": 0.4839632483297185, "tr3.epochs": 283, "tr1.testError": 0.4972845280319937}], [{"tr3.hiddenLayers": 6, "tr1.epochs": 518, "tr1.hiddenLayers": 6, "tr2.epochs": 267, "tr2.testError": 0.4372784890245715, "tr2.hiddenLayers": 6, "tr3.testError": 0.4179902931883259, "tr3.epochs": 267, "tr1.testError": 0.46492503443755007}], [{"tr3.hiddenLayers": 18, "tr1.epochs": 1051, "tr1.hiddenLayers": 14, "tr2.epochs": 537, "tr2.testError": 0.4918215720100454, "tr2.hiddenLayers": 18, "tr3.testError": 0.4098729129646416, "tr3.epochs": 445, "tr1.testError": 0.5804503850523509}], [{"tr3.hiddenLayers": 32, "tr1.epochs": 1051, "tr1.hiddenLayers": 14, "tr2.epochs": 1131, "tr2.testError": 0.49296628827931727, "tr2.hiddenLayers": 21, "tr3.testError": 0.5503559334335182, "tr3.epochs": 1082, "tr1.testError": 0.5804503850523509}], [{"tr3.hiddenLayers": 6, "tr1.epochs": 415, "tr1.hiddenLayers": 6, "tr2.epochs": 259, "tr2.testError": 0.46053030993217653, "tr2.hiddenLayers": 6, "tr3.testError": 0.47212663678072697, "tr3.epochs": 199, "tr1.testError": 0.46089157220023313}], [{"tr3.hiddenLayers": 5, "tr1.epochs": 340, "tr1.hiddenLayers": 5, "tr2.epochs": 184, "tr2.testError": 0.46928213830061627, "tr2.hiddenLayers": 5, "tr3.testError": 0.406966112517756, "tr3.epochs": 134, "tr1.testError": 0.46112759082405924}], [{"tr3.hiddenLayers": 9, "tr1.epochs": 744, "tr1.hiddenLayers": 9, "tr2.epochs": 1068, "tr2.testError": 0.3779588609212276, "tr2.hiddenLayers": 9, "tr3.testError": 0.42659976631978774, "tr3.epochs": 376, "tr1.testError": 0.5031291707741387}], [{"tr3.hiddenLayers": 9, "tr1.epochs": 651, "tr1.hiddenLayers": 9, "tr2.epochs": 354, "tr2.testError": 0.5081085106586211, "tr2.hiddenLayers": 9, "tr3.testError": 0.48714295761929255, "tr3.epochs": 422, "tr1.testError": 0.46742256044795144}], [{"tr3.hiddenLayers": 11, "tr1.epochs": 702, "tr1.hiddenLayers": 11, "tr2.epochs": 455, "tr2.testError": 0.5643908615171238, "tr2.hiddenLayers": 11, "tr3.testError": 0.5673570646215179, "tr3.epochs": 155, "tr1.testError": 0.4587642264999488}]]